mysiar_data_flow/__init__.py
mysiar_data_flow/data_flow.py
mysiar_data_flow/lib/FileType.py
mysiar_data_flow/lib/Operator.py
mysiar_data_flow/lib/__init__.py
mysiar_data_flow/lib/data_columns.py
mysiar_data_flow/lib/data_from.py
mysiar_data_flow/lib/data_to.py
mysiar_data_flow/lib/fireducks.py
mysiar_data_flow/lib/pandas.py
mysiar_data_flow/lib/tools.py
mysiar_data_flow-0.0.2.dist-info/LICENSE
mysiar_data_flow-0.0.2.dist-info/METADATA
mysiar_data_flow-0.0.2.dist-info/WHEEL
mysiar_data_flow-0.0.2.dist-info/RECORD
