Metadata-Version: 2.1
Name: mysiar-data-flow
Version: 0.0.2
Summary: Python data manipulation library
Keywords: dataframe,pandas,polars,fireducks
Author: Piotr Synowiec
Author-email: psynowiec@gmail.com
Maintainer: Piotr Synowiec
Maintainer-email: psynowiec@gmail.com
Requires-Python: >=3.10,<3.13
Classifier: Intended Audience :: Developers
Classifier: License :: OSI Approved :: MIT License
Classifier: Programming Language :: Python :: 3
Classifier: Programming Language :: Python :: 3.10
Classifier: Programming Language :: Python :: 3.11
Classifier: Programming Language :: Python :: 3.12
Classifier: Programming Language :: Python :: 3 :: Only
Classifier: Topic :: Software Development :: Libraries
Classifier: Topic :: Utilities
Provides-Extra: all
Provides-Extra: dev
Requires-Dist: black ; extra == "dev"
Requires-Dist: fireducks
Requires-Dist: flake8 ; extra == "dev"
Requires-Dist: pandas
Requires-Dist: poetry ; extra == "dev"
Requires-Dist: polars
Requires-Dist: pyarrow
Requires-Dist: pyproject-flake8 ; extra == "dev"
Requires-Dist: pytest ; extra == "dev"
Requires-Dist: pytest-cov ; extra == "dev"
Requires-Dist: tables
